emily/__init__.py
emily/emily.py
emily/brain/.DS_Store
emily/brain/README.rst
emily/brain/basic_chat.json
emily/brain/character.json
emily/brain/code_analyzer.yaml
emily/brain/default.json
emily/brain/jokes.yaml
emily/brain/quotes.json
emily/brain/raw_input_test.yaml
emily/brain/sports.json
emily/brain/time_and_date.json
emily/emily_conf/.DS_Store
emily/emily_conf/README.rst
emily/emily_conf/emily_config.yaml
emily/emily_modules/__init__.py
emily/emily_modules/code_analyzer.py
emily/emily_modules/conversations.py
emily/emily_modules/emily_librarian.py
emily/emily_modules/process_input.py
emily/emily_modules/run_command.py
emily/emily_modules/send_message.py
emily/emily_modules/sessions.py
emily/emily_modules/sports.py
emily/emily_modules/utils.py
emily/emily_modules/variables.py
emily/emily_modules/yes_no_parser.py
emily/emily_modules/data/.DS_Store
emily/emily_modules/data/session_vars.json
emily/emily_modules/data/verb.json
emily/emily_modules/data/yesno.json
emily/log/.DS_Store
emily/log/.gitignore
emily/log/emily.log
emily-1.0.8.dist-info/DESCRIPTION.rst
emily-1.0.8.dist-info/METADATA
emily-1.0.8.dist-info/RECORD
emily-1.0.8.dist-info/WHEEL
emily-1.0.8.dist-info/entry_points.txt
emily-1.0.8.dist-info/metadata.json
emily-1.0.8.dist-info/top_level.txt
