Metadata-Version: 2.0
Name: emily
Version: 1.0.8
Summary: A highly customizable chatbot implemented in Python.
Home-page: https://github.com/ngmcfarland/emily
Author: Nathan McFarland
Author-email: ngmcfarland@gmail.com
License: Apache Software License
Download-URL: https://github.com/ngmcfarland/emily/archive/1.0.8.tar.gz
Platform: any
Classifier: Programming Language :: Python
Classifier: Programming Language :: Python :: 2
Classifier: Programming Language :: Python :: 3
Classifier: Development Status :: 4 - Beta
Classifier: Natural Language :: English
Classifier: Intended Audience :: Developers
Classifier: License :: OSI Approved :: Apache Software License
Classifier: Operating System :: OS Independent
Classifier: Topic :: Scientific/Engineering :: Human Machine Interfaces
Classifier: Topic :: Software Development :: Libraries :: Python Modules
Requires-Dist: Flask (>=0.12)
Requires-Dist: Flask-Cors (>=3.0.2)
Requires-Dist: PyYAML (>=3.11)
Requires-Dist: fuzzywuzzy (>=0.15.0)
Requires-Dist: python-Levenshtein (>=0.12.0)
Requires-Dist: six (>=1.10.0)
Provides-Extra: aws
Requires-Dist: boto3 (>=1.4.4); extra == 'aws'
Provides-Extra: testing
Requires-Dist: pytest; extra == 'testing'
